Metadata-Version: 2.1
Name: lotr-api-rr
Version: 0.1.1
Summary: LotR API client
Author: Roman Rochowniak
Author-email: roman.rochowniak@gmail.com
License: BSD
License-File: LICENSE.txt 
